{
  "display": {
    "icon": {
      "item": "aris_random_additions:void_apple"
    },
    "title": {
      "translate": "advancements.void_apple_advancement.title"
    },
    "description": {
      "translate": "advancements.void_apple_advancement.descr"
    },
    "frame": "challenge",
    "show_toast": true,
    "announce_to_chat": true,
    "hidden": false
  },
  "criteria": {
    "void_apple_advancement_0": {
      "trigger": "minecraft:consume_item",
      "conditions": {
        "item": {
          "items": [
            "aris_random_additions:void_apple"
          ]
        }
      }
    }
  },
  "parent": "aris_random_additions:void_star_advancement"
}